{"title":"Ideas and insight about artificial intelligence from MIT Sloan","url":"https://mitsloan.mit.edu/ideas-made-to-matter/artificial-intelligence","favicon":"https://mitsloan.mit.edu/favicon-32x32.png","elements":[{"title":"Considering a platform strategy? The time to move is now","contents":"<div class=\"search-result--eyebrow-wrapper\">\n                            <span class=\"search-result--eyebrow\">\n                    <span>Ideas Made to Matter</span>\n                </span>\n            \n                            <span class=\"search-result--sec-eyebrow\"><a href=\"/ideas-made-to-matter/platform-strategy\">Platform Strategy</a></span>\n                    </div>\n                <h3 class=\"search-result--title\" id=\"title-468827790\">\n                            <a class=\"search-result--title_link\" href=\"/ideas-made-to-matter/considering-a-platform-strategy-time-to-move-now\n                                    \">\n                                        Considering a platform strategy? The time to move is now\n                        </a>        </h3>\n                    <p class=\"blog_post_header--info_label\">By</p>\n            <p class=\"blog_post_header--author\" itemprop=\"author\">\n                                                            Beth Stackpole\n                </p>\n                    <div class=\"search-result--wrap search-result--content\">\n            <p class=\"search-result--description\">  Industry expertise, customer relationships, and willingness to collaborate can help traditional companies compete in the platform market. \n</p>\n                            <div class=\"search-result--info\">\n                    <span class=\"search-result--pub-date\">\n                        <div class=\"search-result--pub-date-icon\" aria-hidden=\"true\"></div>\n                        Aug 4, 2021\n                    </span>\n                </div>\n                    </div>\n                    <a class=\"search-result--link\" id=\"cta-468827790\" aria-labelledby=\"cta-468827790 title-468827790\" data-slot=\"\" title=\"Read Article\" href=\"/ideas-made-to-matter/considering-a-platform-strategy-time-to-move-now\">Read Article</a>\n            <div class=\"linkout-icon\"></div>","link":"https://mitsloan.mit.edu/ideas-made-to-matter/considering-a-platform-strategy-time-to-move-now","retrieved":1628098970670},{"contents":"<p class=\"search-result--description\">  Industry expertise, customer relationships, and willingness to collaborate can help traditional companies compete in the platform market. \n</p>\n                            <div class=\"search-result--info\">\n                    <span class=\"search-result--pub-date\">\n                        <div class=\"search-result--pub-date-icon\" aria-hidden=\"true\"></div>\n                        Aug 4, 2021\n                    </span>\n                </div>","retrieved":1628530884023},{"title":"The CIO role is changing. Here’s what’s next","contents":"<div class=\"search-result--eyebrow-wrapper\">\n                            <span class=\"search-result--eyebrow\">\n                    <span>Ideas Made to Matter</span>\n                </span>\n            \n                            <span class=\"search-result--sec-eyebrow\"><a href=\"/ideas-made-to-matter/innovation\">Innovation</a></span>\n                    </div>\n                <h3 class=\"search-result--title\" id=\"title-1228298264\">\n                            <a class=\"search-result--title_link\" href=\"/ideas-made-to-matter/cio-role-changing-heres-whats-horizon\n                                    \">\n                                        The CIO role is changing. Here’s what’s next\n                        </a>        </h3>\n                    <p class=\"blog_post_header--info_label\">By</p>\n            <p class=\"blog_post_header--author\" itemprop=\"author\">\n                                                            Sara Brown\n                </p>\n                    <div class=\"search-result--wrap search-result--content\">\n            <p class=\"search-result--description\">  Chief information officers are focused on new business models, cloud infrastructure, and working with the C-suite, according to a new survey.  \n</p>\n                            <div class=\"search-result--info\">\n                    <span class=\"search-result--pub-date\">\n                        <div class=\"search-result--pub-date-icon\" aria-hidden=\"true\"></div>\n                        Aug 2, 2021\n                    </span>\n                </div>\n                    </div>\n                    <a class=\"search-result--link\" id=\"cta-1228298264\" aria-labelledby=\"cta-1228298264 title-1228298264\" data-slot=\"\" title=\"Read Article\" href=\"/ideas-made-to-matter/cio-role-changing-heres-whats-horizon\">Read Article</a>\n            <div class=\"linkout-icon\"></div>","link":"https://mitsloan.mit.edu/ideas-made-to-matter/cio-role-changing-heres-whats-horizon","retrieved":1628012773709},{"contents":"<p class=\"search-result--description\">  Chief information officers are focused on new business models, cloud infrastructure, and working with the C-suite, according to a new survey.  \n</p>\n                            <div class=\"search-result--info\">\n                    <span class=\"search-result--pub-date\">\n                        <div class=\"search-result--pub-date-icon\" aria-hidden=\"true\"></div>\n                        Aug 2, 2021\n                    </span>\n                </div>","retrieved":1628530884025},{"title":"Here comes the AI productivity boom","contents":"<div class=\"search-result--eyebrow-wrapper\">\n                            <span class=\"search-result--eyebrow\">\n                    <span>Ideas Made to Matter</span>\n                </span>\n            \n                            <span class=\"search-result--sec-eyebrow\"><a href=\"/ideas-made-to-matter/artificial-intelligence\">Artificial Intelligence</a></span>\n                    </div>\n                <h3 class=\"search-result--title\" id=\"title-710309614\">\n                            <a class=\"search-result--title_link\" href=\"/ideas-made-to-matter/how-to-prepare-ai-productivity-boom\n                                    \">\n                                        Here comes the AI productivity boom\n                        </a>        </h3>\n                    <p class=\"blog_post_header--info_label\">By</p>\n            <p class=\"blog_post_header--author\" itemprop=\"author\">\n                                                            Sara Brown\n                </p>\n                    <div class=\"search-result--wrap search-result--content\">\n            <p class=\"search-result--description\">  Businesses are poised to see big productivity gains from artificial intelligence. Make sure you’re prepared.\n</p>\n                            <div class=\"search-result--info\">\n                    <span class=\"search-result--pub-date\">\n                        <div class=\"search-result--pub-date-icon\" aria-hidden=\"true\"></div>\n                        Jul 12, 2021\n                    </span>\n                </div>\n                    </div>\n                    <a class=\"search-result--link\" id=\"cta-710309614\" aria-labelledby=\"cta-710309614 title-710309614\" data-slot=\"\" title=\"Read Article\" href=\"/ideas-made-to-matter/how-to-prepare-ai-productivity-boom\">Read Article</a>\n            <div class=\"linkout-icon\"></div>","link":"https://mitsloan.mit.edu/ideas-made-to-matter/how-to-prepare-ai-productivity-boom","retrieved":1626154361514},{"contents":"<p class=\"search-result--description\">  Businesses are poised to see big productivity gains from artificial intelligence. Make sure you’re prepared.\n</p>\n                            <div class=\"search-result--info\">\n                    <span class=\"search-result--pub-date\">\n                        <div class=\"search-result--pub-date-icon\" aria-hidden=\"true\"></div>\n                        Jul 12, 2021\n                    </span>\n                </div>","retrieved":1628530884026},{"title":"Digital transformation ideas from MIT Sloan researchers","contents":"<div class=\"search-result--eyebrow-wrapper\">\n                            <span class=\"search-result--eyebrow\">\n                    <span>Ideas Made to Matter</span>\n                </span>\n            \n                            <span class=\"search-result--sec-eyebrow\"><a href=\"/ideas-made-to-matter/digital-economy\">Digital Economy</a></span>\n                    </div>\n                <h3 class=\"search-result--title\" id=\"title-1647832557\">\n                            <a class=\"search-result--title_link\" href=\"/ideas-made-to-matter/4-digital-transformation-insights-mit-sloan-management-review\n                                    \">\n                                        Digital transformation ideas from MIT Sloan researchers\n                        </a>        </h3>\n                    <p class=\"blog_post_header--info_label\">By</p>\n            <p class=\"blog_post_header--author\" itemprop=\"author\">\n                                                            Brian Eastwood\n                </p>\n                    <div class=\"search-result--wrap search-result--content\">\n            <p class=\"search-result--description\">  How to create an \"automation center of excellence\" and develop capabilities for success after the pandemic.\n</p>\n                            <div class=\"search-result--info\">\n                    <span class=\"search-result--pub-date\">\n                        <div class=\"search-result--pub-date-icon\" aria-hidden=\"true\"></div>\n                        Jul 6, 2021\n                    </span>\n                </div>\n                    </div>\n                    <a class=\"search-result--link\" id=\"cta-1647832557\" aria-labelledby=\"cta-1647832557 title-1647832557\" data-slot=\"\" title=\"Read Article\" href=\"/ideas-made-to-matter/4-digital-transformation-insights-mit-sloan-management-review\">Read Article</a>\n            <div class=\"linkout-icon\"></div>","link":"https://mitsloan.mit.edu/ideas-made-to-matter/4-digital-transformation-insights-mit-sloan-management-review","retrieved":1625832816937},{"contents":"<p class=\"search-result--description\">  How to create an \"automation center of excellence\" and develop capabilities for success after the pandemic.\n</p>\n                            <div class=\"search-result--info\">\n                    <span class=\"search-result--pub-date\">\n                        <div class=\"search-result--pub-date-icon\" aria-hidden=\"true\"></div>\n                        Jul 6, 2021\n                    </span>\n                </div>","retrieved":1628530884064},{"title":"Real-world use cases for artificial intelligence","contents":"<div class=\"search-result--eyebrow-wrapper\">\n                            <span class=\"search-result--eyebrow\">\n                    <span>Ideas Made to Matter</span>\n                </span>\n            \n                            <span class=\"search-result--sec-eyebrow\"><a href=\"/ideas-made-to-matter/artificial-intelligence\">Artificial Intelligence</a></span>\n                    </div>\n                <h3 class=\"search-result--title\" id=\"title-1537342480\">\n                            <a class=\"search-result--title_link\" href=\"/ideas-made-to-matter/how-big-firms-leverage-artificial-intelligence-competitive-advantage\n                                    \">\n                                        Real-world use cases for artificial intelligence\n                        </a>        </h3>\n                    <p class=\"blog_post_header--info_label\">By</p>\n            <p class=\"blog_post_header--author\" itemprop=\"author\">\n                                                            Beth Stackpole\n                </p>\n                    <div class=\"search-result--wrap search-result--content\">\n            <p class=\"search-result--description\">  Siemens, Mastercard, and John Deere combine big data with machine learning to improve the customer experience and reduce fraud.\n</p>\n                            <div class=\"search-result--info\">\n                    <span class=\"search-result--pub-date\">\n                        <div class=\"search-result--pub-date-icon\" aria-hidden=\"true\"></div>\n                        May 26, 2021\n                    </span>\n                </div>\n                    </div>\n                    <a class=\"search-result--link\" id=\"cta-1537342480\" aria-labelledby=\"cta-1537342480 title-1537342480\" data-slot=\"\" title=\"Read Article\" href=\"/ideas-made-to-matter/how-big-firms-leverage-artificial-intelligence-competitive-advantage\">Read Article</a>\n            <div class=\"linkout-icon\"></div>","link":"https://mitsloan.mit.edu/ideas-made-to-matter/how-big-firms-leverage-artificial-intelligence-competitive-advantage","retrieved":1625832816937},{"contents":"<p class=\"search-result--description\">  Siemens, Mastercard, and John Deere combine big data with machine learning to improve the customer experience and reduce fraud.\n</p>\n                            <div class=\"search-result--info\">\n                    <span class=\"search-result--pub-date\">\n                        <div class=\"search-result--pub-date-icon\" aria-hidden=\"true\"></div>\n                        May 26, 2021\n                    </span>\n                </div>","retrieved":1628530884066},{"title":"The hidden work created by artificial intelligence programs","contents":"<div class=\"search-result--eyebrow-wrapper\">\n                            <span class=\"search-result--eyebrow\">\n                    <span>Ideas Made to Matter</span>\n                </span>\n            \n                            <span class=\"search-result--sec-eyebrow\"><a href=\"/ideas-made-to-matter/artificial-intelligence\">Artificial Intelligence</a></span>\n                    </div>\n                <h3 class=\"search-result--title\" id=\"title-814065105\">\n                            <a class=\"search-result--title_link\" href=\"/ideas-made-to-matter/hidden-work-created-artificial-intelligence-programs\n                                    \">\n                                        The hidden work created by artificial intelligence programs\n                        </a>        </h3>\n                    <p class=\"blog_post_header--info_label\">By</p>\n            <p class=\"blog_post_header--author\" itemprop=\"author\">\n                                                            Sara Brown\n                </p>\n                    <div class=\"search-result--wrap search-result--content\">\n            <p class=\"search-result--description\">  Successful and ethical artificial intelligence programs take into account behind-the-scenes ‘repair work’ and ‘ghost workers.’   \n</p>\n                            <div class=\"search-result--info\">\n                    <span class=\"search-result--pub-date\">\n                        <div class=\"search-result--pub-date-icon\" aria-hidden=\"true\"></div>\n                        May 4, 2021\n                    </span>\n                </div>\n                    </div>\n                    <a class=\"search-result--link\" id=\"cta-814065105\" aria-labelledby=\"cta-814065105 title-814065105\" data-slot=\"\" title=\"Read Article\" href=\"/ideas-made-to-matter/hidden-work-created-artificial-intelligence-programs\">Read Article</a>\n            <div class=\"linkout-icon\"></div>","link":"https://mitsloan.mit.edu/ideas-made-to-matter/hidden-work-created-artificial-intelligence-programs","retrieved":1625832816937},{"contents":"<p class=\"search-result--description\">  Successful and ethical artificial intelligence programs take into account behind-the-scenes ‘repair work’ and ‘ghost workers.’   \n</p>\n                            <div class=\"search-result--info\">\n                    <span class=\"search-result--pub-date\">\n                        <div class=\"search-result--pub-date-icon\" aria-hidden=\"true\"></div>\n                        May 4, 2021\n                    </span>\n                </div>","retrieved":1628530884110},{"title":"Machine learning, explained","contents":"<div class=\"search-result--eyebrow-wrapper\">\n                            <span class=\"search-result--eyebrow\">\n                    <span>Ideas Made to Matter</span>\n                </span>\n            \n                            <span class=\"search-result--sec-eyebrow\"><a href=\"/ideas-made-to-matter/artificial-intelligence\">Artificial Intelligence</a></span>\n                    </div>\n                <h3 class=\"search-result--title\" id=\"title-1494041701\">\n                            <a class=\"search-result--title_link\" href=\"/ideas-made-to-matter/machine-learning-explained\n                                    \">\n                                        Machine learning, explained \n                        </a>        </h3>\n                    <p class=\"blog_post_header--info_label\">By</p>\n            <p class=\"blog_post_header--author\" itemprop=\"author\">\n                                                            Sara Brown\n                </p>\n                    <div class=\"search-result--wrap search-result--content\">\n            <p class=\"search-result--description\">  Machine learning is a powerful form of artificial intelligence that is affecting every industry. Here’s what you need to know about its potential and limitations and how it’s being used. \n</p>\n                            <div class=\"search-result--info\">\n                    <span class=\"search-result--pub-date\">\n                        <div class=\"search-result--pub-date-icon\" aria-hidden=\"true\"></div>\n                        Apr 21, 2021\n                    </span>\n                </div>\n                    </div>\n                    <a class=\"search-result--link\" id=\"cta-1494041701\" aria-labelledby=\"cta-1494041701 title-1494041701\" data-slot=\"\" title=\"Read Article\" href=\"/ideas-made-to-matter/machine-learning-explained\">Read Article</a>\n            <div class=\"linkout-icon\"></div>","link":"https://mitsloan.mit.edu/ideas-made-to-matter/machine-learning-explained","retrieved":1625832816937},{"contents":"<p class=\"search-result--description\">  Machine learning is a powerful form of artificial intelligence that is affecting every industry. Here’s what you need to know about its potential and limitations and how it’s being used. \n</p>\n                            <div class=\"search-result--info\">\n                    <span class=\"search-result--pub-date\">\n                        <div class=\"search-result--pub-date-icon\" aria-hidden=\"true\"></div>\n                        Apr 21, 2021\n                    </span>\n                </div>","retrieved":1628530884121},{"title":"A ‘break from chaos’ lets this CEO find his best ideas","contents":"<div class=\"search-result--eyebrow-wrapper\">\n                            <span class=\"search-result--eyebrow\">\n                    <span>Ideas Made to Matter</span>\n                </span>\n            \n                            <span class=\"search-result--sec-eyebrow\"><a href=\"/ideas-made-to-matter/my-idea-made-to-matter\">My Idea Made to Matter</a></span>\n                    </div>\n                <h3 class=\"search-result--title\" id=\"title-1529684923\">\n                            <a class=\"search-result--title_link\" href=\"/ideas-made-to-matter/a-break-chaos-lets-ceo-find-his-best-ideas\n                                    \">\n                                        A ‘break from chaos’ lets this CEO find his best ideas\n                        </a>        </h3>\n                    <p class=\"blog_post_header--info_label\">By</p>\n            <p class=\"blog_post_header--author\" itemprop=\"author\">\n                                                            Meredith Somers\n                </p>\n                    <div class=\"search-result--wrap search-result--content\">\n            <p class=\"search-result--description\">  When testing ideas, Remus Capital’s Krishna Gupta errs on the side of action. But if his excitement lags in the face of resistance, he moves on.\n</p>\n                            <div class=\"search-result--info\">\n                    <span class=\"search-result--pub-date\">\n                        <div class=\"search-result--pub-date-icon\" aria-hidden=\"true\"></div>\n                        Apr 14, 2021\n                    </span>\n                </div>\n                    </div>\n                    <a class=\"search-result--link\" id=\"cta-1529684923\" aria-labelledby=\"cta-1529684923 title-1529684923\" data-slot=\"\" title=\"Read Article\" href=\"/ideas-made-to-matter/a-break-chaos-lets-ceo-find-his-best-ideas\">Read Article</a>\n            <div class=\"linkout-icon\"></div>","link":"https://mitsloan.mit.edu/ideas-made-to-matter/a-break-chaos-lets-ceo-find-his-best-ideas","retrieved":1625832816937},{"contents":"<p class=\"search-result--description\">  When testing ideas, Remus Capital’s Krishna Gupta errs on the side of action. But if his excitement lags in the face of resistance, he moves on.\n</p>\n                            <div class=\"search-result--info\">\n                    <span class=\"search-result--pub-date\">\n                        <div class=\"search-result--pub-date-icon\" aria-hidden=\"true\"></div>\n                        Apr 14, 2021\n                    </span>\n                </div>","retrieved":1628530884122},{"title":"7 lessons for successful machine learning projects","contents":"<div class=\"search-result--eyebrow-wrapper\">\n                            <span class=\"search-result--eyebrow\">\n                    <span>Ideas Made to Matter</span>\n                </span>\n            \n                            <span class=\"search-result--sec-eyebrow\"><a href=\"/ideas-made-to-matter/artificial-intelligence\">Artificial Intelligence</a></span>\n                    </div>\n                <h3 class=\"search-result--title\" id=\"title-481555631\">\n                            <a class=\"search-result--title_link\" href=\"/ideas-made-to-matter/7-lessons-to-ensure-successful-machine-learning-projects\n                                    \">\n                                        7 lessons for successful machine learning projects \n                        </a>        </h3>\n                    <p class=\"blog_post_header--info_label\">By</p>\n            <p class=\"blog_post_header--author\" itemprop=\"author\">\n                                                            Sara Brown\n                </p>\n                    <div class=\"search-result--wrap search-result--content\">\n            <p class=\"search-result--description\">  Machine learning success starts with a strong data strategy, the right business use cases, and patience. \n</p>\n                            <div class=\"search-result--info\">\n                    <span class=\"search-result--pub-date\">\n                        <div class=\"search-result--pub-date-icon\" aria-hidden=\"true\"></div>\n                        Apr 6, 2021\n                    </span>\n                </div>\n                    </div>\n                    <a class=\"search-result--link\" id=\"cta-481555631\" aria-labelledby=\"cta-481555631 title-481555631\" data-slot=\"\" title=\"Read Article\" href=\"/ideas-made-to-matter/7-lessons-to-ensure-successful-machine-learning-projects\">Read Article</a>\n            <div class=\"linkout-icon\"></div>","link":"https://mitsloan.mit.edu/ideas-made-to-matter/7-lessons-to-ensure-successful-machine-learning-projects","retrieved":1625832816937},{"contents":"<p class=\"search-result--description\">  Machine learning success starts with a strong data strategy, the right business use cases, and patience. \n</p>\n                            <div class=\"search-result--info\">\n                    <span class=\"search-result--pub-date\">\n                        <div class=\"search-result--pub-date-icon\" aria-hidden=\"true\"></div>\n                        Apr 6, 2021\n                    </span>\n                </div>","retrieved":1628530884130},{"title":"Digital leadership ideas from MIT Sloan researchers","contents":"<div class=\"search-result--eyebrow-wrapper\">\n                            <span class=\"search-result--eyebrow\">\n                    <span>Ideas Made to Matter</span>\n                </span>\n            \n                            <span class=\"search-result--sec-eyebrow\"><a href=\"/ideas-made-to-matter/leadership\">Leadership</a></span>\n                    </div>\n                <h3 class=\"search-result--title\" id=\"title-1985485372\">\n                            <a class=\"search-result--title_link\" href=\"/ideas-made-to-matter/5-insights-digital-leadership-mit-sloan-management-review\n                                    \">\n                                        Digital leadership ideas from MIT Sloan researchers\n                        </a>        </h3>\n                    <p class=\"blog_post_header--info_label\">By</p>\n            <p class=\"blog_post_header--author\" itemprop=\"author\">\n                                                            Brian Eastwood\n                </p>\n                    <div class=\"search-result--wrap search-result--content\">\n            <p class=\"search-result--description\">  The post-pandemic world will reward leaders who navigate a new landscape of digital services to make decisions and encourage innovation.\n</p>\n                            <div class=\"search-result--info\">\n                    <span class=\"search-result--pub-date\">\n                        <div class=\"search-result--pub-date-icon\" aria-hidden=\"true\"></div>\n                        Apr 5, 2021\n                    </span>\n                </div>\n                    </div>\n                    <a class=\"search-result--link\" id=\"cta-1985485372\" aria-labelledby=\"cta-1985485372 title-1985485372\" data-slot=\"\" title=\"Read Article\" href=\"/ideas-made-to-matter/5-insights-digital-leadership-mit-sloan-management-review\">Read Article</a>\n            <div class=\"linkout-icon\"></div>","link":"https://mitsloan.mit.edu/ideas-made-to-matter/5-insights-digital-leadership-mit-sloan-management-review","retrieved":1625832816937},{"contents":"<p class=\"search-result--description\">  The post-pandemic world will reward leaders who navigate a new landscape of digital services to make decisions and encourage innovation.\n</p>\n                            <div class=\"search-result--info\">\n                    <span class=\"search-result--pub-date\">\n                        <div class=\"search-result--pub-date-icon\" aria-hidden=\"true\"></div>\n                        Apr 5, 2021\n                    </span>\n                </div>","retrieved":1628530884130}]}